me_gpt/__init__.py
me_gpt/ai.py
me_gpt/db.py
me_gpt/similarity.py
me_gpt/examples/example.py
me_gpt-0.1.6.dist-info/METADATA
me_gpt-0.1.6.dist-info/WHEEL
me_gpt-0.1.6.dist-info/licenses/LICENSE
me_gpt-0.1.6.dist-info/RECORD
