Metadata-Version: 2.3
Name: me-gpt
Version: 0.1.6
Summary: A python package to clone yourself with the help of LLMs
Project-URL: Homepage, https://github.com/djm93dev/me_gpt
Project-URL: Bug Tracker, https://github.com/djm93dev/me_gpt/issues
Author-email: Daniel McDonald <daniel@danielmcdonald.dev>
Classifier: License :: OSI Approved :: MIT License
Classifier: Operating System :: OS Independent
Classifier: Programming Language :: Python :: 3
Requires-Python: >=3.8
Requires-Dist: numpy
Requires-Dist: openai==0.27.8
Requires-Dist: python-dotenv==1.0.0
